{
  "annotations": {
    "changelogDate": "20251009084852"
  },
  "applications": "*",
  "fields": [
    {
      "fieldName": "baseCurrencyId",
      "fieldType": "Long",
      "fieldValidateRules": ["required"]
    },
    {
      "fieldName": "targetCurrencyId",
      "fieldType": "Long",
      "fieldValidateRules": ["required"]
    },
    {
      "fieldName": "rate",
      "fieldType": "BigDecimal",
      "fieldValidateRules": ["required"]
    },
    {
      "fieldName": "rateDate",
      "fieldType": "Instant",
      "fieldValidateRules": ["required"]
    }
  ],
  "name": "ExchangeRate",
  "pagination": "pagination",
  "relationships": [],
  "searchEngine": "no",
  "service": "serviceClass"
}
