{
  "annotations": {
    "changelogDate": "20251009084904"
  },
  "applications": "*",
  "fields": [
    {
      "fieldName": "quoteId",
      "fieldType": "Long",
      "fieldValidateRules": ["required"]
    },
    {
      "fieldName": "productId",
      "fieldType": "Long"
    },
    {
      "fieldName": "quantity",
      "fieldType": "Integer"
    },
    {
      "fieldName": "unitPrice",
      "fieldType": "BigDecimal"
    },
    {
      "fieldName": "vatRateId",
      "fieldType": "Long"
    }
  ],
  "name": "QuoteLine",
  "pagination": "pagination",
  "relationships": [],
  "searchEngine": "no",
  "service": "serviceClass"
}
